incenp/__init__.py
incenp/davpoint/__init__.py
incenp/davpoint/__main__.py
incenp/davpoint/davfs2.py
incenp/davpoint/sharepoint.py
incenp.davpoint-0.2.1.dist-info/AUTHORS
incenp.davpoint-0.2.1.dist-info/COPYING
incenp.davpoint-0.2.1.dist-info/METADATA
incenp.davpoint-0.2.1.dist-info/WHEEL
incenp.davpoint-0.2.1.dist-info/entry_points.txt
incenp.davpoint-0.2.1.dist-info/top_level.txt
incenp.davpoint-0.2.1.dist-info/RECORD
