Metadata-Version: 2.1
Name: incenp.davpoint
Version: 0.2.1
Summary: Davfs2 wrapper to mount SharePoint filesystems
Home-page: https://git.incenp.org/damien/davpoint
Author: Damien Goutte-Gattat
Author-email: dgouttegattat@incenp.org
License: UNKNOWN
Platform: UNKNOWN
Classifier: Development Status :: 3 - Alpha
Classifier: Environment :: Console
Classifier: Intended Audience :: End Users/Desktop
Classifier: License :: OSI Approved :: GNU General Public License v3 or later (GPLv3+)
Classifier: Programming Language :: Python :: 3
Classifier: Programming Language :: Python :: 3.6
Classifier: Programming Language :: Python :: 3.7
Classifier: Programming Language :: Python :: 3.8
License-File: COPYING
License-File: AUTHORS
Requires-Dist: click
